mixed_fraction/__init__.py
mixed_fraction/mixed_fraction.py
mixed_fraction-0.1.0.dist-info/licenses/LICENSE
tests/test_mixed_fraction.py
mixed_fraction-0.1.0.dist-info/METADATA
mixed_fraction-0.1.0.dist-info/WHEEL
mixed_fraction-0.1.0.dist-info/top_level.txt
mixed_fraction-0.1.0.dist-info/RECORD
