Metadata-Version: 2.4
Name: mixed-fraction
Version: 0.1.0
Summary: Mixed fraction representation with arithmetic operations
Author: Mehmet Efe Coskun
License: MIT
Requires-Python: >=3.10
License-File: LICENSE
Dynamic: license-file
